{
  "brand.name": "Glatko",
  "brand.tagline": "منصة الخدمات المتميزة في الجبل الأسود",
  "brand.description": "محترفون موثوقون لمنزلك وقاربك ونمط حياتك",
  "nav.home": "الرئيسية",
  "nav.services": "الخدمات",
  "nav.howItWorks": "كيف يعمل",
  "nav.becomeAPro": "كن محترفاً",
  "nav.login": "تسجيل الدخول",
  "nav.register": "إنشاء حساب",
  "nav.myAccount": "حسابي",
  "nav.dashboard": "لوحة التحكم",
  "nav.logout": "تسجيل الخروج",
  "nav.requestService": "طلب خدمة",
  "nav.menu": "القائمة",
  "nav.proDashboard": "لوحة المتخصص",
  "hero.title": "محترفون موثوقون في الجبل الأسود",
  "hero.subtitle": "من تنظيف الفلل إلى صيانة القوارب — خدمات احترافية لمنزلك وقاربك",
  "hero.cta": "احصل على عرض سعر مجاني",
  "hero.ctaSecondary": "استعرض المحترفين",
  "hero.trustedBy": "موثوق به في بودفا وكوتور وتيفات",
  "hero.stats.professionals": "محترفون",
  "hero.stats.jobsCompleted": "مهمة منجزة",
  "hero.stats.avgRating": "متوسط التقييم",
  "categories.title": "فئات خدماتنا",
  "categories.subtitle": "اعثر على المحترف المناسب لاحتياجاتك",
  "categories.home.title": "تنظيف المنزل والتجديد",
  "categories.home.description": "تنظيف الفلل، تنظيف عميق، طلاء، كهرباء، سباكة",
  "categories.home.generalCleaning": "تنظيف عام",
  "categories.home.deepCleaning": "تنظيف عميق",
  "categories.home.villaAirbnb": "تنظيف فلل / Airbnb",
  "categories.home.renovation": "تجديد وإعادة تأهيل",
  "categories.home.painting": "طلاء وديكور",
  "categories.home.electrical": "أعمال كهربائية",
  "categories.home.plumbing": "أعمال سباكة",
  "categories.home.acHeating": "تكييف وتدفئة",
  "categories.home.furnitureAssembly": "تركيب أثاث",
  "categories.home.garden": "صيانة الحدائق",
  "categories.home.pool": "تنظيف المسابح",
  "categories.boat.title": "صيانة القوارب وربان",
  "categories.boat.description": "مانع الحشف البحري، صيانة المحرك، استئجار ربان، تنظيف الهيكل",
  "categories.boat.captainHire": "استئجار ربان",
  "categories.boat.antifouling": "مانع الحشف البحري",
  "categories.boat.engineService": "صيانة المحرك",
  "categories.boat.hullCleaning": "تنظيف وتلميع الهيكل",
  "categories.boat.winterization": "تجهيز لفصل الشتاء",
  "categories.boat.charterPrep": "إعداد للتأجير البحري",
  "categories.boat.emergencyRepair": "إصلاح طارئ",
  "categories.boat.haulOut": "سحب ونقل القارب",
  "categories.getQuote": "اطلب عرض سعر",
  "howItWorks.title": "كيف يعمل",
  "howItWorks.subtitle": "خدمة احترافية في 3 خطوات بسيطة",
  "howItWorks.step1.title": "اطلب خدمة",
  "howItWorks.step1.description": "صِف احتياجاتك بالتفصيل وأرفق صوراً",
  "howItWorks.step2.title": "قارن العروض",
  "howItWorks.step2.description": "احصل على عروض أسعار من محترفين موثّقين",
  "howItWorks.step3.title": "أنجز العمل وقيّم",
  "howItWorks.step3.description": "اختر المحترف، أتمّ العمل، شارك تجربتك",
  "trust.title": "لماذا Glatko؟",
  "trust.verified": "محترفون موثّقون",
  "trust.verifiedDesc": "خبراء تم التحقق من هويتهم ومؤهلاتهم",
  "trust.transparent": "أسعار شفافة",
  "trust.transparentDesc": "احصل على عروض متعددة، قارن، واختر الأنسب",
  "trust.reviews": "تقييمات حقيقية",
  "trust.reviewsDesc": "نظام تقييم مزدوج بعد كل مهمة منجزة",
  "trust.multilingual": "دعم متعدد اللغات",
  "trust.multilingualDesc": "متوفر بـ 9 لغات — التركية والإنجليزية والروسية والمزيد",
  "trust.local": "خبرة محلية",
  "trust.localDesc": "محترفون في جميع أنحاء الجبل الأسود، من بودفا إلى كوتور",
  "trust.free": "عروض أسعار مجانية",
  "trust.freeDesc": "طلب عرض السعر مجاني تماماً — الدفع فقط عند إتمام العمل",
  "cta.title": "مستعد للبدء؟",
  "cta.subtitle": "اتخذ الخطوة الأولى — احصل على عرض سعر مجاني خلال 60 ثانية",
  "cta.button": "اطلب خدمة",
  "cta.pro.title": "هل أنت محترف؟",
  "cta.pro.subtitle": "انضم إلى Glatko واكتسب عملاء جدد",
  "cta.pro.button": "سجّل كمحترف",
  "footer.company": "الشركة",
  "footer.about": "من نحن",
  "footer.careers": "الوظائف",
  "footer.contact": "اتصل بنا",
  "footer.legal": "الشؤون القانونية",
  "footer.terms": "شروط الاستخدام",
  "footer.privacy": "سياسة الخصوصية",
  "footer.cookies": "سياسة ملفات تعريف الارتباط",
  "footer.gdpr": "GDPR",
  "footer.support": "الدعم",
  "footer.requestService": "اطلب خدمة",
  "footer.help": "مركز المساعدة",
  "footer.becomeAPro": "كن محترفاً",
  "footer.forPros": "للمحترفين",
  "footer.social": "وسائل التواصل الاجتماعي",
  "footer.copyright": "© 2026 Glatko. جميع الحقوق محفوظة.",
  "footer.madeIn": "صُنع بحب في الجبل الأسود",
  "auth.login": "تسجيل الدخول",
  "auth.register": "إنشاء حساب",
  "auth.email": "البريد الإلكتروني",
  "auth.password": "كلمة المرور",
  "auth.confirmPassword": "تأكيد كلمة المرور",
  "auth.fullName": "الاسم الكامل",
  "auth.forgotPassword": "نسيت كلمة المرور",
  "auth.resetPassword": "إعادة تعيين كلمة المرور",
  "auth.orContinueWith": "أو المتابعة عبر",
  "auth.google": "تسجيل الدخول بحساب Google",
  "auth.noAccount": "ليس لديك حساب؟",
  "auth.hasAccount": "لديك حساب بالفعل؟",
  "auth.registerNow": "سجّل الآن",
  "auth.loginNow": "تسجيل الدخول",
  "auth.resetSent": "تم إرسال رابط إعادة تعيين كلمة المرور",
  "auth.checkEmail": "تحقق من بريدك الإلكتروني",
  "auth.backToLogin": "العودة لتسجيل الدخول",
  "auth.sendResetLink": "إرسال رابط إعادة التعيين",
  "auth.forgotPasswordDesc": "أدخل بريدك الإلكتروني وسنرسل لك رابط إعادة تعيين كلمة المرور",
  "auth.resetLinkSent": "تم إرسال رابط إعادة التعيين",
  "auth.resetPasswordTitle": "تعيين كلمة مرور جديدة",
  "auth.resetPasswordDesc": "أدخل كلمة المرور الجديدة",
  "auth.newPassword": "كلمة المرور الجديدة",
  "auth.updatePassword": "تحديث كلمة المرور",
  "auth.updatePasswordError": "تعذّر تحديث كلمة المرور",
  "auth.passwordMismatch": "كلمتا المرور غير متطابقتين",
  "auth.passwordTooShort": "يجب أن تتكون كلمة المرور من 8 أحرف على الأقل",
  "auth.resetError": "يرجى إدخال عنوان بريد إلكتروني صالح",
  "auth.emailRequired": "البريد الإلكتروني وكلمة المرور مطلوبان",
  "auth.invalidCredentials": "البريد الإلكتروني أو كلمة المرور غير صحيحة",
  "auth.emailNotConfirmed": "لم يتم التحقق من بريدك الإلكتروني بعد",
  "auth.allFieldsRequired": "جميع الحقول مطلوبة",
  "auth.createAccount": "إنشاء حساب",
  "auth.verifyEmail": "تحقق من بريدك الإلكتروني",
  "auth.verifyEmailDesc": "تم إرسال بريد التحقق إلى العنوان",
  "auth.goToLogin": "الانتقال لتسجيل الدخول",
  "auth.freeAccount": "أنشئ حساباً مجانياً",
  "auth.googleError": "فشل تسجيل الدخول بحساب Google",
  "auth.backToHome": "العودة للرئيسية",
  "auth.backToMarketplace": "العودة للمنصة",
  "common.loading": "جاري التحميل...",
  "common.error": "حدث خطأ",
  "common.retry": "حاول مجدداً",
  "common.save": "حفظ",
  "common.cancel": "إلغاء",
  "common.delete": "حذف",
  "common.edit": "تعديل",
  "common.back": "رجوع",
  "common.next": "التالي",
  "common.submit": "إرسال",
  "common.search": "بحث",
  "common.filter": "تصفية",
  "common.sort": "ترتيب",
  "common.all": "الكل",
  "common.viewAll": "عرض الكل",
  "common.seeMore": "المزيد",
  "common.close": "إغلاق",
  "common.yes": "نعم",
  "common.no": "لا",
  "common.or": "أو",
  "common.free": "مجاني",
  "common.verified": "موثّق",
  "common.new": "جديد",
  "common.popular": "شائع",
  "common.recommended": "موصى به",
  "common.comingSoon": "قريباً",
  "common.learnMore": "اعرف المزيد",
  "common.backToHome": "العودة للرئيسية",
  "common.notFound": "الصفحة غير موجودة",
  "common.notFoundDesc": "الصفحة التي تبحث عنها غير موجودة أو تم نقلها.",
  "common.errorDesc": "حدث خطأ غير متوقع. يرجى المحاولة مرة أخرى.",
  "meta.home.title": "Glatko — منصة الخدمات المتميزة في الجبل الأسود",
  "meta.home.description": "محترفون موثوقون لتنظيف الفلل وصيانة القوارب والمزيد في الجبل الأسود. احصل على عرض سعر مجاني.",
  "legal.comingSoon": "هذه الصفحة قيد الإعداد.",
  "legal.about": "من نحن",
  "legal.terms": "شروط الاستخدام",
  "legal.privacy": "سياسة الخصوصية",
  "legal.cookies": "سياسة ملفات تعريف الارتباط",
  "legal.gdpr": "GDPR",
  "legal.contact": "اتصل بنا",
  "pro.becomeAPro": "كن محترفاً",
  "pro.wizard.step1Title": "المعلومات الشخصية",
  "pro.wizard.step2Title": "مجالات الخدمة",
  "pro.wizard.step3Title": "المحفظة والمستندات",
  "pro.wizard.businessName": "اسم الشركة",
  "pro.wizard.businessNamePlaceholder": "اختياري",
  "pro.wizard.bio": "عن نفسك",
  "pro.wizard.bioPlaceholder": "خبرتك، مجالات تخصصك...",
  "pro.wizard.phone": "الهاتف",
  "pro.wizard.city": "المدينة",
  "pro.wizard.languages": "اللغات المحكية",
  "pro.wizard.experience": "الخبرة (سنوات)",
  "pro.wizard.hourlyRate": "نطاق الأجر بالساعة (يورو)",
  "pro.wizard.min": "الحد الأدنى",
  "pro.wizard.max": "الحد الأقصى",
  "pro.wizard.selectCategories": "اختر مجالات خدمتك",
  "pro.wizard.primaryService": "مجال الخدمة الرئيسي",
  "pro.wizard.portfolio": "صور المحفظة",
  "pro.wizard.portfolioDesc": "ارفع صور أفضل أعمالك (بحد أقصى 10)",
  "pro.wizard.idDocument": "وثيقة هوية",
  "pro.wizard.idDocumentDesc": "جواز سفر أو بطاقة هوية (مطلوب)",
  "pro.wizard.businessLicense": "رخصة تجارية",
  "pro.wizard.certificates": "الشهادات",
  "pro.wizard.insurance": "وثيقة تأمين",
  "pro.wizard.submit": "إرسال الطلب",
  "pro.wizard.success": "تم استلام طلبك!",
  "pro.wizard.successDesc": "طلبك قيد المراجعة. سيتم إعلامك عبر البريد الإلكتروني.",
  "pro.wizard.alreadyPro": "أنت مسجل بالفعل كمحترف",
  "pro.wizard.uploadFile": "رفع ملف",
  "pro.wizard.uploading": "جارٍ الرفع...",
  "pro.wizard.step": "خطوة",
  "pro.wizard.of": "من",
  "pro.profile.about": "حول",
  "pro.profile.services": "الخدمات",
  "pro.profile.portfolio": "المحفظة",
  "pro.profile.reviews": "التقييمات",
  "pro.profile.noReviews": "لا توجد تقييمات بعد",
  "pro.profile.noPortfolio": "لا توجد محفظة بعد",
  "pro.profile.noServices": "لم يتم إدراج خدمات بعد",
  "pro.profile.verified": "محترف موثق",
  "pro.profile.newPro": "محترف جديد",
  "pro.profile.topPro": "محترف مميز",
  "pro.profile.yearsExp": "سنوات خبرة",
  "pro.profile.completedJobs": "أعمال مكتملة",
  "pro.profile.responseTime": "دقيقة وقت الاستجابة",
  "pro.profile.requestQuote": "اطلب عرض سعر",
  "pro.profile.languages": "اللغات",
  "pro.profile.rating": "التقييم",
  "pro.profile.location": "الموقع",
  "pro.profile.hourlyRate": "الأجر بالساعة",
  "pro.profile.perHour": "/ ساعة",
  "admin.professionals.title": "طلبات المحترفين",
  "admin.professionals.pending": "قيد الانتظار",
  "admin.professionals.inReview": "قيد المراجعة",
  "admin.professionals.approved": "تمت الموافقة",
  "admin.professionals.rejected": "مرفوض",
  "admin.professionals.approve": "موافقة",
  "admin.professionals.reject": "رفض",
  "admin.professionals.takeReview": "أخذ للمراجعة",
  "admin.professionals.rejectReason": "سبب الرفض",
  "admin.professionals.viewDocuments": "عرض المستندات",
  "admin.professionals.noApplications": "لا توجد طلبات بعد",
  "admin.professionals.allStatuses": "جميع الحالات",
  "admin.professionals.filterByCity": "تصفية حسب المدينة",
  "admin.professionals.allCities": "جميع المدن",
  "admin.professionals.applicant": "المتقدم",
  "admin.professionals.serviceAreas": "مجالات الخدمة",
  "admin.professionals.appliedAt": "تاريخ التقديم",
  "admin.professionals.status": "الحالة",
  "admin.professionals.actions": "الإجراءات",
  "admin.professionals.documents": "المستندات",
  "admin.professionals.personalInfo": "المعلومات الشخصية",
  "admin.professionals.confirmApprove": "هل أنت متأكد أنك تريد الموافقة على هذا المحترف؟",
  "admin.professionals.confirmReject": "هل أنت متأكد أنك تريد رفض هذا الطلب؟",
  "admin.professionals.approved_success": "تمت الموافقة على المحترف بنجاح",
  "admin.professionals.rejected_success": "تم رفض الطلب",
  "pro.wizard.title": "كن محترفاً",
  "pro.wizard.subtitle": "انضم إلى Glatko وتواصل مع العملاء في جميع أنحاء الجبل الأسود",
  "pro.wizard.back": "رجوع",
  "pro.wizard.next": "التالي",
  "pro.wizard.step2Desc": "اختر الخدمات التي تقدمها",
  "pro.wizard.step3Desc": "ارفع محفظتك ومستنداتك",
  "pro.wizard.selectCity": "اختر مدينة",
  "pro.wizard.hourlyMin": "الحد الأدنى للأجر (يورو)",
  "pro.wizard.hourlyMax": "الحد الأقصى للأجر (يورو)",
  "pro.wizard.portfolioUpload": "صور المحفظة",
  "pro.wizard.documentsUpload": "مستندات التحقق",
  "pro.wizard.comingSoon": "رفع الملفات قريباً",
  "pro.wizard.reviewNote": "سيتم مراجعة طلبك من قبل فريقنا خلال 24-48 ساعة.",
  "cities.budva": "بودفا",
  "cities.kotor": "كوتور",
  "cities.tivat": "تيفات",
  "cities.podgorica": "بودغوريتسا",
  "cities.hercegNovi": "هيرتسغ نوي",
  "cities.bar": "بار",
  "cities.ulcinj": "أولسيني",
  "request.title": "اطلب خدمة",
  "request.subtitle": "سنجد المحترف المناسب لاحتياجاتك",
  "request.step1.title": "ما نوع الخدمة التي تبحث عنها؟",
  "request.step1.selectCategory": "اختر فئة",
  "request.step1.selectSubcategory": "اختر فئة فرعية",
  "request.step2.title": "حدد التفاصيل",
  "request.step2.propertyType": "نوع العقار",
  "request.step2.apartment": "شقة",
  "request.step2.villa": "فيلا",
  "request.step2.studio": "استوديو",
  "request.step2.office": "مكتب",
  "request.step2.roomCount": "عدد الغرف",
  "request.step2.areaSqm": "المساحة (م²)",
  "request.step2.frequency": "تكرار التنظيف",
  "request.step2.oneTime": "مرة واحدة",
  "request.step2.weekly": "أسبوعي",
  "request.step2.monthly": "شهري",
  "request.step2.regular": "عقد منتظم",
  "request.step2.jobType": "نوع العمل",
  "request.step2.fullRenovation": "تجديد كامل",
  "request.step2.partial": "تجديد جزئي",
  "request.step2.kitchenOnly": "المطبخ فقط",
  "request.step2.bathroomOnly": "الحمام فقط",
  "request.step2.terrace": "شرفة / تراس",
  "request.step2.issueType": "نوع المشكلة",
  "request.step2.newInstallation": "تركيب جديد",
  "request.step2.repair": "إصلاح",
  "request.step2.maintenance": "صيانة / فحص",
  "request.step2.relocation": "نقل",
  "request.step2.isUrgent": "هل هو عاجل؟",
  "request.step2.boatType": "نوع القارب",
  "request.step2.motorYacht": "يخت محرك",
  "request.step2.sailboat": "قارب شراعي",
  "request.step2.catamaran": "كاتاماران",
  "request.step2.speedboat": "زورق سريع",
  "request.step2.gulet": "جوليت",
  "request.step2.boatLength": "طول القارب (متر)",
  "request.step2.tripDuration": "المدة",
  "request.step2.daily": "يومي",
  "request.step2.weeklyTrip": "أسبوعي",
  "request.step2.transfer": "نقل",
  "request.step2.licenseRequired": "هل يلزم ترخيص؟",
  "request.step2.engineType": "نوع المحرك",
  "request.step2.inboard": "داخلي",
  "request.step2.outboard": "خارجي",
  "request.step2.sailNoEngine": "شراع (بدون محرك)",
  "request.step2.marina": "مارينا",
  "request.step2.notes": "ملاحظات إضافية",
  "request.step2.notesPlaceholder": "تفاصيل إضافية...",
  "request.step3.title": "الموقع والتوقيت",
  "request.step3.city": "المدينة",
  "request.step3.address": "العنوان (اختياري)",
  "request.step3.addressPlaceholder": "الحي، الشارع أو وصف المنطقة",
  "request.step3.when": "متى؟",
  "request.step3.urgent48h": "عاجل (خلال 48 ساعة)",
  "request.step3.thisWeek": "هذا الأسبوع",
  "request.step3.flexible": "مرن",
  "request.step3.specificDate": "تاريخ محدد",
  "request.step3.startDate": "تاريخ البدء",
  "request.step3.endDate": "تاريخ الانتهاء (اختياري)",
  "request.step4.title": "الصور والإرسال",
  "request.step4.photos": "أضف صوراً",
  "request.step4.photosDesc": "أظهر احتياجاتك بالصور (بحد أقصى 5)",
  "request.step4.dragDrop": "اسحب وأفلت أو انقر للاختيار",
  "request.step4.skipPhotos": "تابع بدون صور",
  "request.step4.budget": "الميزانية التقديرية",
  "request.step4.budgetOptional": "احصل على عروض من المحترفين",
  "request.step4.budgetMin": "الحد الأدنى (يورو)",
  "request.step4.budgetMax": "الحد الأقصى (يورو)",
  "request.step4.phone": "رقم الهاتف",
  "request.step4.email": "البريد الإلكتروني (اختياري)",
  "request.step4.requestTitle": "عنوان الطلب",
  "request.step4.autoTitle": "تم إنشاؤه تلقائياً — عدّل إذا أردت",
  "request.step4.description": "الوصف (اختياري)",
  "request.step4.descriptionPlaceholder": "صف احتياجاتك باختصار",
  "request.step4.submit": "إرسال طلب الخدمة",
  "request.step4.submitting": "جارٍ إرسال طلبك...",
  "request.confirmation.title": "تم إرسال طلبك بنجاح!",
  "request.confirmation.subtitle": "ستبدأ في تلقي عروض من المحترفين",
  "request.confirmation.summary": "ملخص الطلب",
  "request.confirmation.goToRequests": "انتقل إلى طلباتي",
  "request.confirmation.createAnother": "إنشاء طلب جديد",
  "dashboard.title": "لوحة التحكم",
  "dashboard.requests.title": "طلباتي",
  "dashboard.requests.all": "الكل",
  "dashboard.requests.active": "نشط",
  "dashboard.requests.completed": "مكتمل",
  "dashboard.requests.cancelled": "ملغى",
  "dashboard.requests.empty": "ليس لديك طلبات خدمة بعد",
  "dashboard.requests.createFirst": "أنشئ طلبك الأول",
  "dashboard.requests.bidsReceived": "عروض مستلمة",
  "dashboard.requests.detail.title": "تفاصيل الطلب",
  "dashboard.requests.detail.status": "الحالة",
  "dashboard.requests.detail.category": "الفئة",
  "dashboard.requests.detail.location": "الموقع",
  "dashboard.requests.detail.date": "تفضيل التاريخ",
  "dashboard.requests.detail.budget": "الميزانية",
  "dashboard.requests.detail.description": "الوصف",
  "dashboard.requests.detail.details": "التفاصيل",
  "dashboard.requests.detail.photos": "الصور",
  "dashboard.requests.detail.bids": "العروض",
  "dashboard.requests.detail.noBids": "لا توجد عروض بعد — المحترفون يراجعون",
  "dashboard.requests.detail.cancel": "إلغاء الطلب",
  "dashboard.requests.detail.cancelConfirm": "هل أنت متأكد أنك تريد إلغاء هذا الطلب؟",
  "dashboard.requests.detail.edit": "تعديل",
  "status.draft": "مسودة",
  "status.published": "منشور",
  "status.bidding": "العروض واردة",
  "status.assigned": "معيّن",
  "status.inProgress": "قيد التنفيذ",
  "status.completed": "مكتمل",
  "status.reviewed": "تم التقييم",
  "status.closed": "مغلق",
  "status.expired": "منتهي الصلاحية",
  "status.cancelled": "ملغى",
  "request.wizard.title": "اطلب خدمة",
  "request.wizard.subtitle": "سنجد المحترف المناسب لاحتياجاتك",
  "request.wizard.back": "رجوع",
  "request.wizard.next": "التالي",
  "request.wizard.submit": "إرسال طلب الخدمة",
  "request.error.generic": "حدث خطأ. يرجى المحاولة مرة أخرى.",
  "request.step1.subtitle": "اختر فئة خدمة للبدء",
  "request.step1.selectSub": "اختر فئة فرعية",
  "request.step2.subtitle": "ساعدنا لفهم احتياجاتك بشكل أفضل",
  "request.step2.house": "منزل",
  "request.step2.rooms": "عدد الغرف",
  "request.step2.areaRange": "المساحة التقريبية",
  "request.step2.area.small": "صغير (<50 م²)",
  "request.step2.area.medium": "متوسط (50-100 م²)",
  "request.step2.area.large": "كبير (100-200 م²)",
  "request.step2.area.xlarge": "كبير جداً (200+ م²)",
  "request.step2.freq.oneTime": "مرة واحدة",
  "request.step2.freq.weekly": "أسبوعي",
  "request.step2.freq.biweekly": "كل أسبوعين",
  "request.step2.freq.monthly": "شهري",
  "request.step2.job.interior": "داخلي",
  "request.step2.job.exterior": "خارجي",
  "request.step2.job.fullReno": "تجديد كامل",
  "request.step2.job.partialReno": "تجديد جزئي",
  "request.step2.job.wallPaint": "دهان الجدران",
  "request.step2.job.ceilingPaint": "دهان السقف",
  "request.step2.issue.repair": "إصلاح",
  "request.step2.issue.installation": "تركيب جديد",
  "request.step2.issue.inspection": "فحص",
  "request.step2.issue.replacement": "استبدال",
  "request.step2.issue.other": "أخرى",
  "request.step2.urgent": "هل هو عاجل؟",
  "request.step2.description": "الوصف",
  "request.step2.descriptionPlaceholder": "صف ما تحتاجه...",
  "request.step2.emergencyPlaceholder": "صف حالة الطوارئ بالتفصيل...",
  "request.step2.boat.sailboat": "قارب شراعي",
  "request.step2.boat.motorboat": "قارب محرك",
  "request.step2.boat.catamaran": "كاتاماران",
  "request.step2.boat.yacht": "يخت",
  "request.step2.boatLengthPlaceholder": "مثلاً 12",
  "request.step2.hasLicense": "هل لديك رخصة؟",
  "request.step2.trip.halfDay": "نصف يوم",
  "request.step2.trip.fullDay": "يوم كامل",
  "request.step2.trip.multiDay": "عدة أيام",
  "request.step2.trip.weekly": "أسبوعي",
  "request.step2.engine.inboard": "داخلي",
  "request.step2.engine.outboard": "خارجي",
  "request.step2.engine.diesel": "ديزل",
  "request.step2.engine.electric": "كهربائي",
  "request.step2.selectMarina": "اختر مارينا",
  "request.step3.subtitle": "أين ومتى تحتاج الخدمة؟",
  "request.step3.selectCity": "اختر مدينة",
  "request.step3.marina": "مارينا",
  "request.step3.selectMarina": "اختر مارينا",
  "request.step3.urgency": "متى؟",
  "request.step3.urgency.urgent48h": "عاجل (48 ساعة)",
  "request.step3.urgency.thisWeek": "هذا الأسبوع",
  "request.step3.urgency.flexible": "مرن",
  "request.step3.urgency.specificDate": "تاريخ محدد",
  "request.step3.dateStart": "تاريخ البدء",
  "request.step3.dateEnd": "تاريخ الانتهاء (اختياري)",
  "request.step4.subtitle": "أضف صوراً وأكمل طلبك",
  "request.step4.dragOrClick": "اسحب وأفلت أو انقر للاختيار",
  "request.step4.phonePlaceholder": "+382 XX XXX XXX",
  "request.step4.emailPlaceholder": "بريدك@email.com",
  "request.step4.titlePlaceholder": "مثلاً تنظيف فيلا - بودفا",
  "request.confirmation.category": "الفئة",
  "request.confirmation.city": "المدينة",
  "request.confirmation.urgency": "الاستعجال",
  "request.confirmation.budget": "الميزانية",
  "dashboard.detail.cancelRequest": "إلغاء الطلب",
  "dashboard.detail.cancelConfirm": "هل أنت متأكد أنك تريد إلغاء هذا الطلب؟",
  "dashboard.detail.cancelError": "فشل الإلغاء. يرجى المحاولة مرة أخرى.",
  "dashboard.detail.confirmCancel": "نعم، إلغاء",
  "dashboard.detail.keepRequest": "الاحتفاظ بالطلب",
  "dashboard.requests.subtitle": "تتبع وأدر طلبات الخدمة الخاصة بك",
  "dashboard.requests.emptyDesc": "أنشئ طلب خدمتك الأول واحصل على عروض من المحترفين",
  "dashboard.requests.bids": "عروض",
  "dashboard.requests.status.draft": "مسودة",
  "dashboard.requests.status.published": "منشور",
  "dashboard.requests.status.bidding": "العروض واردة",
  "dashboard.requests.status.assigned": "معيّن",
  "dashboard.requests.status.in_progress": "قيد التنفيذ",
  "dashboard.requests.status.completed": "مكتمل",
  "dashboard.requests.status.reviewed": "تم التقييم",
  "dashboard.requests.status.closed": "مغلق",
  "dashboard.requests.status.expired": "منتهي الصلاحية",
  "dashboard.requests.status.cancelled": "ملغى",
  "dashboard.detail.back": "العودة للطلبات",
  "dashboard.detail.timeline": "التقدم",
  "dashboard.detail.details": "التفاصيل",
  "dashboard.detail.photos": "الصور",
  "dashboard.detail.bids": "العروض",
  "dashboard.detail.noBids": "لا توجد عروض بعد — المحترفون يراجعون طلبك",
  "dashboard.detail.anonymous": "محترف مجهول",
  "proDashboard.title": "لوحة المتخصص",
  "proDashboard.welcome": "أهلاً وسهلاً",
  "proDashboard.stats.pendingBids": "العروض المعلقة",
  "proDashboard.stats.activeJobs": "الأعمال النشطة",
  "proDashboard.stats.completedJobs": "الأعمال المكتملة",
  "proDashboard.nav.home": "الرئيسية",
  "proDashboard.nav.requests": "الطلبات المطابقة",
  "proDashboard.nav.bids": "عروضي",
  "proDashboard.nav.profile": "ملفي الشخصي",
  "proDashboard.nav.settings": "الإعدادات",
  "proDashboard.notApproved": "طلبك قيد المراجعة",
  "proDashboard.notApprovedDesc": "يمكنك تقديم العروض بعد اكتمال التحقق",
  "proRequests.title": "الطلبات المطابقة",
  "proRequests.subtitle": "الطلبات المفتوحة المطابقة لخدماتك",
  "proRequests.empty": "لا توجد طلبات مطابقة حالياً",
  "proRequests.emptyDesc": "سيتم إشعارك عند وصول طلبات جديدة",
  "proRequests.filter.all": "الكل",
  "proRequests.filter.homeServices": "خدمات منزلية",
  "proRequests.filter.boatServices": "خدمات بحرية",
  "proRequests.sort.newest": "الأحدث",
  "proRequests.sort.budgetHigh": "الميزانية (الأعلى)",
  "proRequests.sort.urgentFirst": "العاجل أولاً",
  "proRequests.card.budget": "الميزانية",
  "proRequests.card.photos": "صور",
  "proRequests.card.bidsReceived": "عروض مستلمة",
  "proRequests.card.viewDetail": "عرض التفاصيل",
  "proRequests.card.submitBid": "تقديم عرض",
  "proRequests.card.ago": "مضت",
  "bidForm.title": "تقديم عرض",
  "bidForm.price": "السعر (EUR)",
  "bidForm.priceType": "نوع السعر",
  "bidForm.fixed": "سعر ثابت",
  "bidForm.hourly": "بالساعة",
  "bidForm.estimate": "تقدير",
  "bidForm.message": "رسالتك",
  "bidForm.messagePlaceholder": "عرّف عن نفسك، اوصف خبرتك ونهجك...",
  "bidForm.estimatedDuration": "المدة المقدرة (ساعات)",
  "bidForm.availableDate": "تاريخ التوفر",
  "bidForm.submit": "إرسال العرض",
  "bidForm.submitting": "جارٍ إرسال عرضك...",
  "bidForm.success": "تم إرسال عرضك!",
  "bidForm.successDesc": "سيتم إشعارك عندما يراجع العميل عرضك",
  "bidForm.maxBidsReached": "تم الوصول للحد الأقصى من العروض لهذا الطلب",
  "bidForm.alreadyBid": "لقد قدمت عرضاً بالفعل لهذا الطلب",
  "bids.title": "عروضي",
  "bids.all": "الكل",
  "bids.pending": "معلقة",
  "bids.accepted": "مقبولة",
  "bids.rejected": "مرفوضة",
  "bids.withdrawn": "مسحوبة",
  "bids.empty": "لم تقدم أي عروض بعد",
  "bids.emptyDesc": "يمكنك تقديم عروض من قسم الطلبات المطابقة",
  "bids.withdraw": "سحب",
  "bids.withdrawConfirm": "هل أنت متأكد من رغبتك في سحب هذا العرض؟",
  "bids.yourPrice": "عرضك",
  "bids.requestStatus": "حالة الطلب",
  "bids.bidStatus": "حالة العرض",
  "bidComparison.title": "العروض",
  "bidComparison.noBids": "لا توجد عروض بعد — المتخصصون يراجعون طلبك",
  "bidComparison.waitingBids": "المتخصصون يراجعون...",
  "bidComparison.bidsCount": "عروض مستلمة",
  "bidComparison.bestMatch": "أفضل تطابق",
  "bidComparison.viewProfile": "عرض الملف الشخصي",
  "bidComparison.sendMessage": "إرسال رسالة",
  "bidComparison.accept": "قبول",
  "bidComparison.acceptConfirm": "هل أنت متأكد من رغبتك في قبول هذا العرض؟",
  "bidComparison.acceptConfirmDesc": "سيتم رفض العروض الأخرى تلقائياً.",
  "bidComparison.accepted": "المتخصص المعين",
  "bidComparison.rejected": "مرفوض",
  "bidComparison.rating": "تقييمات",
  "bidComparison.available": "متاح",
  "bidComparison.duration": "المدة المقدرة",
  "bidComparison.assignedSuccess": "تم تعيين المتخصص بنجاح!",
  "bidComparison.hours": "ساعات"
}
